slb_glossary/__init__.py
slb_glossary/exceptions.py
slb_glossary/glossary.py
slb_glossary/saver.py
slb_glossary-0.0.1.dist-info/LICENSE
slb_glossary-0.0.1.dist-info/METADATA
slb_glossary-0.0.1.dist-info/WHEEL
slb_glossary-0.0.1.dist-info/top_level.txt
slb_glossary-0.0.1.dist-info/RECORD
