Metadata-Version: 2.1
Name: slb_glossary
Version: 0.0.1
Summary: Search the Schlumberger Oilfield Glossary programmatically using Selenium.
Author-email: "Daniel T. Afolayan (ti-oluwa)" <tioluwa.dev@gmail.com>
Maintainer-email: "Daniel T. Afolayan (ti-oluwa)" <tioluwa.dev@gmail.com>
Project-URL: Homepage, https://github.com/ti-oluwa/slb_glossary
Project-URL: Bug Tracker, https://github.com/ti-oluwa/slb_glossary/issues
Project-URL: Repository, https://github.com/ti-oluwa/slb_glossary
Keywords: Schlumberger,Oilfield,Glossary,Petroleum terms,Petroleum
Classifier: Programming Language :: Python :: 3
Classifier: License :: OSI Approved :: MIT License
Classifier: Operating System :: OS Independent
Classifier: Development Status :: 4 - Beta
Classifier: Environment :: Console
Requires-Python: >=3.7
License-File: LICENSE
Requires-Dist: selenium>=4.10.0
